setup.cfg
setup.py
SajadKM/__init__.py
SajadKM.egg-info/PKG-INFO
SajadKM.egg-info/SOURCES.txt
SajadKM.egg-info/dependency_links.txt
SajadKM.egg-info/top_level.txt