Metadata-Version: 2.1
Name: SajadKM
Version: 0.1
Summary: TOOC
Author: Sajad @K_D_QQ
Author-email: lahauiva@gmail.com
Classifier: Programming Language :: Python :: 3
Classifier: License :: OSI Approved :: MIT License
Classifier: Operating System :: OS Independent
